avnet/iotconnect/sdk/greengrass/__init__.py
avnet/iotconnect/sdk/greengrass/client.py
avnet/iotconnect/sdk/greengrass/config.py
iotconnect_greengrass_sdk-1.0.0.dist-info/licenses/LICENSE.md
iotconnect_greengrass_sdk-1.0.0.dist-info/METADATA
iotconnect_greengrass_sdk-1.0.0.dist-info/WHEEL
iotconnect_greengrass_sdk-1.0.0.dist-info/top_level.txt
iotconnect_greengrass_sdk-1.0.0.dist-info/RECORD
