Metadata-Version: 2.4
Name: iotconnect-greengrass-sdk
Version: 1.0.0
Summary: Avnet IoTConnect Greengrass SDK
Author-email: Nik Markovic <nikola.markovic@avnet.com>
Project-URL: Homepage, https://github.com/avnet-iotconnect/iotc-python-greengrass-sdk
Keywords: /IOTCONNECT,AWS,Greengrass,IoTCore
Classifier: Development Status :: 3 - Alpha
Classifier: Intended Audience :: Developers
Classifier: License :: OSI Approved :: MIT License
Classifier: Natural Language :: English
Classifier: Operating System :: MacOS :: MacOS X
Classifier: Operating System :: Microsoft :: Windows
Classifier: Operating System :: POSIX
Classifier: Programming Language :: Python
Classifier: Programming Language :: Python :: 3
Classifier: Programming Language :: Python :: 3.9
Classifier: Programming Language :: Python :: 3.10
Classifier: Programming Language :: Python :: 3.11
Classifier: Programming Language :: Python :: 3.12
Classifier: Programming Language :: Python :: 3.13
Classifier: Programming Language :: Python :: 3.14
Classifier: Topic :: Communications
Classifier: Topic :: Internet
Requires-Python: >=3.9
License-File: LICENSE.md
Requires-Dist: iotconnect-lib<2.0.0
Requires-Dist: awsiotsdk<2.0.0
Dynamic: license-file
